odb_plotter/__init__.py
odb_plotter/__main__.py
odb_plotter/cli.py
odb_plotter/npz_to_hdf.py
odb_plotter/odb.py
odb_plotter/odb_visualizer.py
odb_plotter/read_hdf5.py
odb_plotter/util.py
odb_plotter_static/odb_to_npz.py
odb_plotter_static/views.json
ODBPlotter-0.0.3.dist-info/LICENSE.md
ODBPlotter-0.0.3.dist-info/METADATA
ODBPlotter-0.0.3.dist-info/WHEEL
ODBPlotter-0.0.3.dist-info/entry_points.txt
ODBPlotter-0.0.3.dist-info/top_level.txt
ODBPlotter-0.0.3.dist-info/RECORD
