Metadata-Version: 2.1
Name: ODBPlotter
Version: 0.0.3
Summary: TODO
Author-email: Clark Hensley <clarkhensley@duck.com>
Maintainer-email: Clark Hensley <clarkhensley@duck.com>
Project-URL: Homepage, https://www.cmml.me.msstate.edu
Project-URL: Bug Reports, https://www.github.com/mwpriddy/ODBPlotter/issues
Project-URL: Source, https://www.github.com/mwpriddy/ODBPlotter
Keywords: TODO
License-File: LICENSE.md
Requires-Dist: h5py
Requires-Dist: numpy
Requires-Dist: pandas
Requires-Dist: matplotlib
